Workbook

Sheet Dashboard
B1: ReelsWave — Financial Dashboard
B2: 12-Month Forward Projection | Update subscriber counts in 'Monthly Tracker'
B4: KEY ANNUAL METRICS
B5: Annual Revenue | C5: Annual Costs | D5: Net Profit | E5: Gross Margin | F5: Total Subscribers | G5: Avg MRR
B6: ='Monthly Tracker'!K16 | C6: ='Monthly Tracker'!N16 | D6: ='Monthly Tracker'!O16 | E6: ='Monthly Tracker'!P16 | F6: ='Monthly Tracker'!H16 | G6: =IFERROR('Monthly Tracker'!K16/12,0)
B8: MONTHLY BREAKDOWN
B9: Month | C9: Total Subs | D9: Total MRR | E9: Total Costs | F9: Net Profit | G9: Margin
B10: Mar 2026 | C10: ='Monthly Tracker'!H4 | D10: ='Monthly Tracker'!K4 | E10: ='Monthly Tracker'!N4 | F10: ='Monthly Tracker'!O4 | G10: ='Monthly Tracker'!P4
B11: Apr 2026 | C11: ='Monthly Tracker'!H5 | D11: ='Monthly Tracker'!K5 | E11: ='Monthly Tracker'!N5 | F11: ='Monthly Tracker'!O5 | G11: ='Monthly Tracker'!P5
B12: May 2026 | C12: ='Monthly Tracker'!H6 | D12: ='Monthly Tracker'!K6 | E12: ='Monthly Tracker'!N6 | F12: ='Monthly Tracker'!O6 | G12: ='Monthly Tracker'!P6
B13: Jun 2026 | C13: ='Monthly Tracker'!H7 | D13: ='Monthly Tracker'!K7 | E13: ='Monthly Tracker'!N7 | F13: ='Monthly Tracker'!O7 | G13: ='Monthly Tracker'!P7
B14: Jul 2026 | C14: ='Monthly Tracker'!H8 | D14: ='Monthly Tracker'!K8 | E14: ='Monthly Tracker'!N8 | F14: ='Monthly Tracker'!O8 | G14: ='Monthly Tracker'!P8
B15: Aug 2026 | C15: ='Monthly Tracker'!H9 | D15: ='Monthly Tracker'!K9 | E15: ='Monthly Tracker'!N9 | F15: ='Monthly Tracker'!O9 | G15: ='Monthly Tracker'!P9
B16: Sep 2026 | C16: ='Monthly Tracker'!H10 | D16: ='Monthly Tracker'!K10 | E16: ='Monthly Tracker'!N10 | F16: ='Monthly Tracker'!O10 | G16: ='Monthly Tracker'!P10
B17: Oct 2026 | C17: ='Monthly Tracker'!H11 | D17: ='Monthly Tracker'!K11 | E17: ='Monthly Tracker'!N11 | F17: ='Monthly Tracker'!O11 | G17: ='Monthly Tracker'!P11
B18: Nov 2026 | C18: ='Monthly Tracker'!H12 | D18: ='Monthly Tracker'!K12 | E18: ='Monthly Tracker'!N12 | F18: ='Monthly Tracker'!O12 | G18: ='Monthly Tracker'!P12
B19: Dec 2026 | C19: ='Monthly Tracker'!H13 | D19: ='Monthly Tracker'!K13 | E19: ='Monthly Tracker'!N13 | F19: ='Monthly Tracker'!O13 | G19: ='Monthly Tracker'!P13
B20: Jan 2027 | C20: ='Monthly Tracker'!H14 | D20: ='Monthly Tracker'!K14 | E20: ='Monthly Tracker'!N14 | F20: ='Monthly Tracker'!O14 | G20: ='Monthly Tracker'!P14
B21: Feb 2027 | C21: ='Monthly Tracker'!H15 | D21: ='Monthly Tracker'!K15 | E21: ='Monthly Tracker'!N15 | F21: ='Monthly Tracker'!O15 | G21: ='Monthly Tracker'!P15
B22: ANNUAL TOTAL | C22: ='Monthly Tracker'!H16 | D22: ='Monthly Tracker'!K16 | E22: ='Monthly Tracker'!N16 | F22: ='Monthly Tracker'!O16 | G22: ='Monthly Tracker'!P16
B24: HOW TO USE
B25: 1. Assumptions tab → update any API costs or plan pricing (blue cells).
B26: 2. Monthly Tracker tab → enter your subscriber count per plan each month (blue cells).
B27: 3. All revenue, costs, and profit calculate automatically from those two inputs.
B28: 4. This dashboard reflects the tracker in real time — no manual updates needed.

Sheet Assumptions
A1: ReelsWave — Cost & Pricing Assumptions
A3: COST PER VIDEO
A4: Component | B4: Cost ($)
A5: Images (AI generation) | B5: 0.05
A6: ElevenLabs — Short Form (30–60s) | B6: 0.2
A7: ElevenLabs — Long Form (60–90s) | B7: 0.3
A8: Gemini (Script Generation) | B8: 0.01
A9: Total Cost — Short Form | B9: =B5+B6+B8
A10: Total Cost — Long Form | B10: =B5+B7+B8
A12: PLAN PRICING — MONTHLY
A13: Plan | B13: Price / Mo ($) | C13: Videos / Mo | D13: % Long Form
A14: Starter Monthly | B14: 9 | C14: 12 | D14: 0.5
A15: Pro Monthly | B15: 29 | C15: 30 | D15: 0.6
A16: Dedicated Monthly | B16: 79 | C16: 90 | D16: 0.7
A18: PLAN PRICING — YEARLY (billed annually)
A19: Plan | B19: Price / Yr ($) | C19: Videos / Mo | D19: % Long Form
A20: Starter Yearly | B20: 90 | C20: 12 | D20: 0.5
A21: Pro Yearly | B21: 290 | C21: 30 | D21: 0.6
A22: Dedicated Yearly | B22: 790 | C22: 90 | D22: 0.7
A24: FIXED MONTHLY COSTS
A25: Item | B25: Cost / Mo ($)
A26: Railway (Hosting) | B26: 0
A27: Supabase (Database) | B27: 0
A28: Domain / DNS | B28: 1
A29: ElevenLabs Base Subscription | B29: 0
A30: Other | B30: 0
A31: Total Fixed Monthly | B31: =SUM(B26:B30)
A33: Color Guide:
A34: Blue = Input (edit these)
A35: Black = Formula (do not edit)
A36: Green = Cross-sheet link

Sheet Monthly Tracker
A1: ReelsWave — Monthly Revenue & Cost Tracker
B2: SUBSCRIBERS ← enter values here | I2: REVENUE | L2: COSTS | O2: PROFIT
A3: Month | B3: Starter (Mo) | C3: Pro (Mo) | D3: Dedicated (Mo) | E3: Starter (Yr) | F3: Pro (Yr) | G3: Dedicated (Yr) | H3: Total Subs | I3: MRR Monthly | J3: MRR Yearly | K3: Total MRR | L3: Variable Costs | M3: Fixed Costs | N3: Total Costs | O3: Net Profit | P3: Margin
A4: Mar 2026 | B4: 0 | C4: 0 | D4: 0 | E4: 0 | F4: 0 | G4: 0 | H4: =SUM(B4:G4) | I4: =B4*Assumptions!B14+C4*Assumptions!B15+D4*Assumptions!B16 | J4: =E4*Assumptions!B20/12+F4*Assumptions!B21/12+G4*Assumptions!B22/12 | K4: =I4+J4 | L4: =B4*Assumptions!C14*(Assumptions!D14*Assumptions!B10+(1-Assumptions!D14)*Assumptions!B9)+C4*Assumptions!C15*(Assumptions!D15*Assumptions!B10+(1-Assumptions!D15)*Assumptions!B9)+D4*Assumptions!C16*(Assumptions!D16*Assumptions!B10+(1-Assumptions!D16)*Assumptions!B9)+E4*Assumptions!C20*(Assumptions!D20*Assumptions!B10+(1-Assumptions!D20)*Assumptions!B9)+F4*Assumptions!C21*(Assumptions!D21*Assumptions!B10+(1-Assumptions!D21)*Assumptions!B9)+G4*Assumptions!C22*(Assumptions!D22*Assumptions!B10+(1-Assumptions!D22)*Assumptions!B9) | M4: =Assumptions!B31 | N4: =L4+M4 | O4: =K4-N4 | P4: =IFERROR((K4-N4)/K4,0)
A5: Apr 2026 | B5: 0 | C5: 0 | D5: 0 | E5: 0 | F5: 0 | G5: 0 | H5: =SUM(B5:G5) | I5: =B5*Assumptions!B14+C5*Assumptions!B15+D5*Assumptions!B16 | J5: =E5*Assumptions!B20/12+F5*Assumptions!B21/12+G5*Assumptions!B22/12 | K5: =I5+J5 | L5: =B5*Assumptions!C14*(Assumptions!D14*Assumptions!B10+(1-Assumptions!D14)*Assumptions!B9)+C5*Assumptions!C15*(Assumptions!D15*Assumptions!B10+(1-Assumptions!D15)*Assumptions!B9)+D5*Assumptions!C16*(Assumptions!D16*Assumptions!B10+(1-Assumptions!D16)*Assumptions!B9)+E5*Assumptions!C20*(Assumptions!D20*Assumptions!B10+(1-Assumptions!D20)*Assumptions!B9)+F5*Assumptions!C21*(Assumptions!D21*Assumptions!B10+(1-Assumptions!D21)*Assumptions!B9)+G5*Assumptions!C22*(Assumptions!D22*Assumptions!B10+(1-Assumptions!D22)*Assumptions!B9) | M5: =Assumptions!B31 | N5: =L5+M5 | O5: =K5-N5 | P5: =IFERROR((K5-N5)/K5,0)
A6: May 2026 | B6: 0 | C6: 0 | D6: 0 | E6: 0 | F6: 0 | G6: 0 | H6: =SUM(B6:G6) | I6: =B6*Assumptions!B14+C6*Assumptions!B15+D6*Assumptions!B16 | J6: =E6*Assumptions!B20/12+F6*Assumptions!B21/12+G6*Assumptions!B22/12 | K6: =I6+J6 | L6: =B6*Assumptions!C14*(Assumptions!D14*Assumptions!B10+(1-Assumptions!D14)*Assumptions!B9)+C6*Assumptions!C15*(Assumptions!D15*Assumptions!B10+(1-Assumptions!D15)*Assumptions!B9)+D6*Assumptions!C16*(Assumptions!D16*Assumptions!B10+(1-Assumptions!D16)*Assumptions!B9)+E6*Assumptions!C20*(Assumptions!D20*Assumptions!B10+(1-Assumptions!D20)*Assumptions!B9)+F6*Assumptions!C21*(Assumptions!D21*Assumptions!B10+(1-Assumptions!D21)*Assumptions!B9)+G6*Assumptions!C22*(Assumptions!D22*Assumptions!B10+(1-Assumptions!D22)*Assumptions!B9) | M6: =Assumptions!B31 | N6: =L6+M6 | O6: =K6-N6 | P6: =IFERROR((K6-N6)/K6,0)
A7: Jun 2026 | B7: 0 | C7: 0 | D7: 0 | E7: 0 | F7: 0 | G7: 0 | H7: =SUM(B7:G7) | I7: =B7*Assumptions!B14+C7*Assumptions!B15+D7*Assumptions!B16 | J7: =E7*Assumptions!B20/12+F7*Assumptions!B21/12+G7*Assumptions!B22/12 | K7: =I7+J7 | L7: =B7*Assumptions!C14*(Assumptions!D14*Assumptions!B10+(1-Assumptions!D14)*Assumptions!B9)+C7*Assumptions!C15*(Assumptions!D15*Assumptions!B10+(1-Assumptions!D15)*Assumptions!B9)+D7*Assumptions!C16*(Assumptions!D16*Assumptions!B10+(1-Assumptions!D16)*Assumptions!B9)+E7*Assumptions!C20*(Assumptions!D20*Assumptions!B10+(1-Assumptions!D20)*Assumptions!B9)+F7*Assumptions!C21*(Assumptions!D21*Assumptions!B10+(1-Assumptions!D21)*Assumptions!B9)+G7*Assumptions!C22*(Assumptions!D22*Assumptions!B10+(1-Assumptions!D22)*Assumptions!B9) | M7: =Assumptions!B31 | N7: =L7+M7 | O7: =K7-N7 | P7: =IFERROR((K7-N7)/K7,0)
A8: Jul 2026 | B8: 0 | C8: 0 | D8: 0 | E8: 0 | F8: 0 | G8: 0 | H8: =SUM(B8:G8) | I8: =B8*Assumptions!B14+C8*Assumptions!B15+D8*Assumptions!B16 | J8: =E8*Assumptions!B20/12+F8*Assumptions!B21/12+G8*Assumptions!B22/12 | K8: =I8+J8 | L8: =B8*Assumptions!C14*(Assumptions!D14*Assumptions!B10+(1-Assumptions!D14)*Assumptions!B9)+C8*Assumptions!C15*(Assumptions!D15*Assumptions!B10+(1-Assumptions!D15)*Assumptions!B9)+D8*Assumptions!C16*(Assumptions!D16*Assumptions!B10+(1-Assumptions!D16)*Assumptions!B9)+E8*Assumptions!C20*(Assumptions!D20*Assumptions!B10+(1-Assumptions!D20)*Assumptions!B9)+F8*Assumptions!C21*(Assumptions!D21*Assumptions!B10+(1-Assumptions!D21)*Assumptions!B9)+G8*Assumptions!C22*(Assumptions!D22*Assumptions!B10+(1-Assumptions!D22)*Assumptions!B9) | M8: =Assumptions!B31 | N8: =L8+M8 | O8: =K8-N8 | P8: =IFERROR((K8-N8)/K8,0)
A9: Aug 2026 | B9: 0 | C9: 0 | D9: 0 | E9: 0 | F9: 0 | G9: 0 | H9: =SUM(B9:G9) | I9: =B9*Assumptions!B14+C9*Assumptions!B15+D9*Assumptions!B16 | J9: =E9*Assumptions!B20/12+F9*Assumptions!B21/12+G9*Assumptions!B22/12 | K9: =I9+J9 | L9: =B9*Assumptions!C14*(Assumptions!D14*Assumptions!B10+(1-Assumptions!D14)*Assumptions!B9)+C9*Assumptions!C15*(Assumptions!D15*Assumptions!B10+(1-Assumptions!D15)*Assumptions!B9)+D9*Assumptions!C16*(Assumptions!D16*Assumptions!B10+(1-Assumptions!D16)*Assumptions!B9)+E9*Assumptions!C20*(Assumptions!D20*Assumptions!B10+(1-Assumptions!D20)*Assumptions!B9)+F9*Assumptions!C21*(Assumptions!D21*Assumptions!B10+(1-Assumptions!D21)*Assumptions!B9)+G9*Assumptions!C22*(Assumptions!D22*Assumptions!B10+(1-Assumptions!D22)*Assumptions!B9) | M9: =Assumptions!B31 | N9: =L9+M9 | O9: =K9-N9 | P9: =IFERROR((K9-N9)/K9,0)
A10: Sep 2026 | B10: 0 | C10: 0 | D10: 0 | E10: 0 | F10: 0 | G10: 0 | H10: =SUM(B10:G10) | I10: =B10*Assumptions!B14+C10*Assumptions!B15+D10*Assumptions!B16 | J10: =E10*Assumptions!B20/12+F10*Assumptions!B21/12+G10*Assumptions!B22/12 | K10: =I10+J10 | L10: =B10*Assumptions!C14*(Assumptions!D14*Assumptions!B10+(1-Assumptions!D14)*Assumptions!B9)+C10*Assumptions!C15*(Assumptions!D15*Assumptions!B10+(1-Assumptions!D15)*Assumptions!B9)+D10*Assumptions!C16*(Assumptions!D16*Assumptions!B10+(1-Assumptions!D16)*Assumptions!B9)+E10*Assumptions!C20*(Assumptions!D20*Assumptions!B10+(1-Assumptions!D20)*Assumptions!B9)+F10*Assumptions!C21*(Assumptions!D21*Assumptions!B10+(1-Assumptions!D21)*Assumptions!B9)+G10*Assumptions!C22*(Assumptions!D22*Assumptions!B10+(1-Assumptions!D22)*Assumptions!B9) | M10: =Assumptions!B31 | N10: =L10+M10 | O10: =K10-N10 | P10: =IFERROR((K10-N10)/K10,0)
A11: Oct 2026 | B11: 0 | C11: 0 | D11: 0 | E11: 0 | F11: 0 | G11: 0 | H11: =SUM(B11:G11) | I11: =B11*Assumptions!B14+C11*Assumptions!B15+D11*Assumptions!B16 | J11: =E11*Assumptions!B20/12+F11*Assumptions!B21/12+G11*Assumptions!B22/12 | K11: =I11+J11 | L11: =B11*Assumptions!C14*(Assumptions!D14*Assumptions!B10+(1-Assumptions!D14)*Assumptions!B9)+C11*Assumptions!C15*(Assumptions!D15*Assumptions!B10+(1-Assumptions!D15)*Assumptions!B9)+D11*Assumptions!C16*(Assumptions!D16*Assumptions!B10+(1-Assumptions!D16)*Assumptions!B9)+E11*Assumptions!C20*(Assumptions!D20*Assumptions!B10+(1-Assumptions!D20)*Assumptions!B9)+F11*Assumptions!C21*(Assumptions!D21*Assumptions!B10+(1-Assumptions!D21)*Assumptions!B9)+G11*Assumptions!C22*(Assumptions!D22*Assumptions!B10+(1-Assumptions!D22)*Assumptions!B9) | M11: =Assumptions!B31 | N11: =L11+M11 | O11: =K11-N11 | P11: =IFERROR((K11-N11)/K11,0)
A12: Nov 2026 | B12: 0 | C12: 0 | D12: 0 | E12: 0 | F12: 0 | G12: 0 | H12: =SUM(B12:G12) | I12: =B12*Assumptions!B14+C12*Assumptions!B15+D12*Assumptions!B16 | J12: =E12*Assumptions!B20/12+F12*Assumptions!B21/12+G12*Assumptions!B22/12 | K12: =I12+J12 | L12: =B12*Assumptions!C14*(Assumptions!D14*Assumptions!B10+(1-Assumptions!D14)*Assumptions!B9)+C12*Assumptions!C15*(Assumptions!D15*Assumptions!B10+(1-Assumptions!D15)*Assumptions!B9)+D12*Assumptions!C16*(Assumptions!D16*Assumptions!B10+(1-Assumptions!D16)*Assumptions!B9)+E12*Assumptions!C20*(Assumptions!D20*Assumptions!B10+(1-Assumptions!D20)*Assumptions!B9)+F12*Assumptions!C21*(Assumptions!D21*Assumptions!B10+(1-Assumptions!D21)*Assumptions!B9)+G12*Assumptions!C22*(Assumptions!D22*Assumptions!B10+(1-Assumptions!D22)*Assumptions!B9) | M12: =Assumptions!B31 | N12: =L12+M12 | O12: =K12-N12 | P12: =IFERROR((K12-N12)/K12,0)
A13: Dec 2026 | B13: 0 | C13: 0 | D13: 0 | E13: 0 | F13: 0 | G13: 0 | H13: =SUM(B13:G13) | I13: =B13*Assumptions!B14+C13*Assumptions!B15+D13*Assumptions!B16 | J13: =E13*Assumptions!B20/12+F13*Assumptions!B21/12+G13*Assumptions!B22/12 | K13: =I13+J13 | L13: =B13*Assumptions!C14*(Assumptions!D14*Assumptions!B10+(1-Assumptions!D14)*Assumptions!B9)+C13*Assumptions!C15*(Assumptions!D15*Assumptions!B10+(1-Assumptions!D15)*Assumptions!B9)+D13*Assumptions!C16*(Assumptions!D16*Assumptions!B10+(1-Assumptions!D16)*Assumptions!B9)+E13*Assumptions!C20*(Assumptions!D20*Assumptions!B10+(1-Assumptions!D20)*Assumptions!B9)+F13*Assumptions!C21*(Assumptions!D21*Assumptions!B10+(1-Assumptions!D21)*Assumptions!B9)+G13*Assumptions!C22*(Assumptions!D22*Assumptions!B10+(1-Assumptions!D22)*Assumptions!B9) | M13: =Assumptions!B31 | N13: =L13+M13 | O13: =K13-N13 | P13: =IFERROR((K13-N13)/K13,0)
A14: Jan 2027 | B14: 0 | C14: 0 | D14: 0 | E14: 0 | F14: 0 | G14: 0 | H14: =SUM(B14:G14) | I14: =B14*Assumptions!B14+C14*Assumptions!B15+D14*Assumptions!B16 | J14: =E14*Assumptions!B20/12+F14*Assumptions!B21/12+G14*Assumptions!B22/12 | K14: =I14+J14 | L14: =B14*Assumptions!C14*(Assumptions!D14*Assumptions!B10+(1-Assumptions!D14)*Assumptions!B9)+C14*Assumptions!C15*(Assumptions!D15*Assumptions!B10+(1-Assumptions!D15)*Assumptions!B9)+D14*Assumptions!C16*(Assumptions!D16*Assumptions!B10+(1-Assumptions!D16)*Assumptions!B9)+E14*Assumptions!C20*(Assumptions!D20*Assumptions!B10+(1-Assumptions!D20)*Assumptions!B9)+F14*Assumptions!C21*(Assumptions!D21*Assumptions!B10+(1-Assumptions!D21)*Assumptions!B9)+G14*Assumptions!C22*(Assumptions!D22*Assumptions!B10+(1-Assumptions!D22)*Assumptions!B9) | M14: =Assumptions!B31 | N14: =L14+M14 | O14: =K14-N14 | P14: =IFERROR((K14-N14)/K14,0)
A15: Feb 2027 | B15: 0 | C15: 0 | D15: 0 | E15: 0 | F15: 0 | G15: 0 | H15: =SUM(B15:G15) | I15: =B15*Assumptions!B14+C15*Assumptions!B15+D15*Assumptions!B16 | J15: =E15*Assumptions!B20/12+F15*Assumptions!B21/12+G15*Assumptions!B22/12 | K15: =I15+J15 | L15: =B15*Assumptions!C14*(Assumptions!D14*Assumptions!B10+(1-Assumptions!D14)*Assumptions!B9)+C15*Assumptions!C15*(Assumptions!D15*Assumptions!B10+(1-Assumptions!D15)*Assumptions!B9)+D15*Assumptions!C16*(Assumptions!D16*Assumptions!B10+(1-Assumptions!D16)*Assumptions!B9)+E15*Assumptions!C20*(Assumptions!D20*Assumptions!B10+(1-Assumptions!D20)*Assumptions!B9)+F15*Assumptions!C21*(Assumptions!D21*Assumptions!B10+(1-Assumptions!D21)*Assumptions!B9)+G15*Assumptions!C22*(Assumptions!D22*Assumptions!B10+(1-Assumptions!D22)*Assumptions!B9) | M15: =Assumptions!B31 | N15: =L15+M15 | O15: =K15-N15 | P15: =IFERROR((K15-N15)/K15,0)
A16: ANNUAL TOTAL | B16: =SUM(B4:B15) | C16: =SUM(C4:C15) | D16: =SUM(D4:D15) | E16: =SUM(E4:E15) | F16: =SUM(F4:F15) | G16: =SUM(G4:G15) | H16: =SUM(H4:H15) | I16: =SUM(I4:I15) | ... O16: =SUM(O4:O15) | P16: =IFERROR((K16-N16)/K16,0)
